pyghelper/__init__.py
pyghelper/animation_manager.py
pyghelper/config.py
pyghelper/event_manager.py
pyghelper/images.py
pyghelper/sound_manager.py
pyghelper/utils.py
pyghelper-0.0.3.dist-info/LICENSE
pyghelper-0.0.3.dist-info/METADATA
pyghelper-0.0.3.dist-info/WHEEL
pyghelper-0.0.3.dist-info/top_level.txt
pyghelper-0.0.3.dist-info/RECORD
