Metadata-Version: 2.1
Name: pyghelper
Version: 0.0.3
Summary: Functions and classes to help use PyGame (WIP)
Home-page: https://www.github.com/charon25/PythonGameHelper
Author: Paul 'charon25' Kern
License: MIT
Requires-Python: >=3.11
License-File: LICENSE
Requires-Dist: pygame >=2.0.1
